panoptes/__init__.py
panoptes/pocs/__init__.py
panoptes/pocs/base.py
panoptes/pocs/core.py
panoptes/pocs/hardware.py
panoptes/pocs/images.py
panoptes/pocs/observatory.py
panoptes/pocs/camera/__init__.py
panoptes/pocs/camera/camera.py
panoptes/pocs/camera/fli.py
panoptes/pocs/camera/libasi.py
panoptes/pocs/camera/libfli.py
panoptes/pocs/camera/libfliconstants.py
panoptes/pocs/camera/sbig.py
panoptes/pocs/camera/sbigudrv.py
panoptes/pocs/camera/sdk.py
panoptes/pocs/camera/zwo.py
panoptes/pocs/camera/gphoto/__init__.py
panoptes/pocs/camera/gphoto/base.py
panoptes/pocs/camera/gphoto/canon.py
panoptes/pocs/camera/gphoto/remote.py
panoptes/pocs/camera/simulator/__init__.py
panoptes/pocs/camera/simulator/ccd.py
panoptes/pocs/camera/simulator/dslr.py
panoptes/pocs/dome/__init__.py
panoptes/pocs/dome/abstract_serial_dome.py
panoptes/pocs/dome/astrohaven.py
panoptes/pocs/dome/bisque.py
panoptes/pocs/dome/protocol_astrohaven_simulator.py
panoptes/pocs/dome/simulator.py
panoptes/pocs/filterwheel/__init__.py
panoptes/pocs/filterwheel/filterwheel.py
panoptes/pocs/filterwheel/libefw.py
panoptes/pocs/filterwheel/sbig.py
panoptes/pocs/filterwheel/simulator.py
panoptes/pocs/filterwheel/zwo.py
panoptes/pocs/focuser/__init__.py
panoptes/pocs/focuser/astromechanics.py
panoptes/pocs/focuser/birger.py
panoptes/pocs/focuser/focuser.py
panoptes/pocs/focuser/focuslynx.py
panoptes/pocs/focuser/serial.py
panoptes/pocs/focuser/simulator.py
panoptes/pocs/mount/__init__.py
panoptes/pocs/mount/bisque.py
panoptes/pocs/mount/mount.py
panoptes/pocs/mount/serial.py
panoptes/pocs/mount/simulator.py
panoptes/pocs/mount/ioptron/__init__.py
panoptes/pocs/mount/ioptron/cem40.py
panoptes/pocs/mount/ioptron/ieq30pro.py
panoptes/pocs/scheduler/__init__.py
panoptes/pocs/scheduler/constraint.py
panoptes/pocs/scheduler/dispatch.py
panoptes/pocs/scheduler/field.py
panoptes/pocs/scheduler/scheduler.py
panoptes/pocs/scheduler/observation/__init__.py
panoptes/pocs/scheduler/observation/base.py
panoptes_pocs-0.7.8.dist-info/AUTHORS.rst
panoptes_pocs-0.7.8.dist-info/LICENSE.txt
panoptes_pocs-0.7.8.dist-info/METADATA
panoptes_pocs-0.7.8.dist-info/WHEEL
panoptes_pocs-0.7.8.dist-info/entry_points.txt
panoptes_pocs-0.7.8.dist-info/top_level.txt
panoptes_pocs-0.7.8.dist-info/RECORD
