Metadata-Version: 2.1
Name: panoptes-pocs
Version: 0.7.8
Summary: PANOPTES Observatory Control System
Home-page: https://github.com/panoptes/POCS
Author: Project PANOPTES
Author-email: developers@projectpanoptes.org
License: mit
Project-URL: Documentation, https://panoptes-pocs.readthedocs.org
Project-URL: Forum, https://forum.projectpanoptes.org
Platform: linux
Classifier: Development Status :: 4 - Beta
Classifier: Environment :: Console
Classifier: Intended Audience :: Science/Research
Classifier: License :: OSI Approved :: MIT License
Classifier: Operating System :: POSIX
Classifier: Programming Language :: Python :: 3
Classifier: Programming Language :: Python :: 3.9
Classifier: Programming Language :: Python :: 3 :: Only
Classifier: Topic :: Scientific/Engineering :: Astronomy
Classifier: Topic :: Scientific/Engineering :: Physics
Requires-Python: >=3.9
License-File: LICENSE.txt
License-File: AUTHORS.rst
Requires-Dist: astroplan
Requires-Dist: astropy
Requires-Dist: fastapi
Requires-Dist: panoptes-utils[config] (>=0.2.35)
Requires-Dist: pandas
Requires-Dist: Pillow (>=8.3.2)
Requires-Dist: pyserial
Requires-Dist: requests
Requires-Dist: transitions
Requires-Dist: uvicorn[standard]
Provides-Extra: focuser
Requires-Dist: matplotlib ; extra == 'focuser'
Requires-Dist: scipy ; extra == 'focuser'
Provides-Extra: google
Requires-Dist: google-cloud-storage ; extra == 'google'
Requires-Dist: gsutil ; extra == 'google'
Provides-Extra: sensors
Requires-Dist: streamz ; extra == 'sensors'
Provides-Extra: testing
Requires-Dist: coverage ; extra == 'testing'
Requires-Dist: mocket ; extra == 'testing'
Requires-Dist: pycodestyle ; extra == 'testing'
Requires-Dist: pytest ; extra == 'testing'
Requires-Dist: pytest-cov ; extra == 'testing'
Requires-Dist: pytest-doctestplus ; extra == 'testing'
Requires-Dist: pytest-remotedata (>=0.3.1) ; extra == 'testing'
Requires-Dist: responses ; extra == 'testing'
